esgf_playground_utils/__init__.py
esgf_playground_utils/config/__init__.py
esgf_playground_utils/config/kafka.py
esgf_playground_utils/models/__init__.py
esgf_playground_utils/models/kafka.py
esgf_playground_utils-1.0.5.dist-info/LICENSE
esgf_playground_utils-1.0.5.dist-info/METADATA
esgf_playground_utils-1.0.5.dist-info/WHEEL
esgf_playground_utils-1.0.5.dist-info/RECORD
