Metadata-Version: 2.3
Name: esgf-playground-utils
Version: 1.0.5
Summary: Common library and models for the ESGF-Playground
Author: David Poulter
Author-email: david.poulter@stfc.ac.uk
Requires-Python: >=3.10,<4.0
Classifier: Programming Language :: Python :: 3
Classifier: Programming Language :: Python :: 3.10
Classifier: Programming Language :: Python :: 3.11
Classifier: Programming Language :: Python :: 3.12
Classifier: Programming Language :: Python :: 3.13
Requires-Dist: jinja2 (>=3.1.6,<4.0.0)
Requires-Dist: pydantic-settings (>=2.6.1,<3.0.0)
Requires-Dist: stac-fastapi.extensions (==6.0.0)
Requires-Dist: stac-pydantic (>=3.1.1,<4.0.0)
